stac_fastapi/eodag/__init__.py
stac_fastapi/eodag/api.py
stac_fastapi/eodag/app.py
stac_fastapi/eodag/client.py
stac_fastapi/eodag/config.py
stac_fastapi/eodag/constants.py
stac_fastapi/eodag/core.py
stac_fastapi/eodag/cql_evaluate.py
stac_fastapi/eodag/dag.py
stac_fastapi/eodag/errors.py
stac_fastapi/eodag/logs.py
stac_fastapi/eodag/middlewares.py
stac_fastapi/eodag/telemetry.py
stac_fastapi/eodag/utils.py
stac_fastapi/eodag/eodag_types/__init__.py
stac_fastapi/eodag/eodag_types/queryables.py
stac_fastapi/eodag/eodag_types/search.py
stac_fastapi/eodag/extensions/collection_order.py
stac_fastapi/eodag/extensions/data_download.py
stac_fastapi/eodag/extensions/ecmwf.py
stac_fastapi/eodag/extensions/filter.py
stac_fastapi/eodag/extensions/offset_pagination.py
stac_fastapi/eodag/extensions/pagination.py
stac_fastapi/eodag/extensions/stac.py
stac_fastapi/eodag/models/__init__.py
stac_fastapi/eodag/models/links.py
stac_fastapi/eodag/models/stac_metadata.py
stac_fastapi_eodag-0.1.0.dist-info/licenses/LICENSE
stac_fastapi_eodag-0.1.0.dist-info/METADATA
stac_fastapi_eodag-0.1.0.dist-info/WHEEL
stac_fastapi_eodag-0.1.0.dist-info/top_level.txt
stac_fastapi_eodag-0.1.0.dist-info/RECORD
