Metadata-Version: 2.4
Name: stac_fastapi.eodag
Version: 0.1.0
Summary: A stac-fastapi backend using EODAG
Author-email: "CS GROUP - France (CSSI)" <eodag@csgroup.space>
License: 
Project-URL: Homepage, https://github.com/CS-SI/stac-fastapi-eodag
Project-URL: Repository, https://github.com/CS-SI/stac-fastapi-eodag.git
Project-URL: Bug Tracker, https://github.com/CS-SI/stac-fastapi-eodag/issues/
Requires-Python: >=3.9
License-File: LICENSE
Requires-Dist: attr
Requires-Dist: eodag[all-providers]
Requires-Dist: fastapi
Requires-Dist: geojson-pydantic
Requires-Dist: orjson
Requires-Dist: pydantic
Requires-Dist: pydantic_core
Requires-Dist: pygeofilter
Requires-Dist: stac-fastapi.api>=4.0
Requires-Dist: stac-fastapi.extensions
Requires-Dist: stac-fastapi.types
Requires-Dist: stac-pydantic==3.1.*
Requires-Dist: brotli-asgi
Requires-Dist: starlette
Requires-Dist: typing_extensions
Requires-Dist: shapely
Provides-Extra: server
Requires-Dist: uvicorn[standard]; extra == "server"
Provides-Extra: telemetry
Requires-Dist: opentelemetry-api; extra == "telemetry"
Requires-Dist: opentelemetry-sdk; extra == "telemetry"
Requires-Dist: opentelemetry-exporter-otlp-proto-http; extra == "telemetry"
Requires-Dist: opentelemetry-instrumentation-eodag>=0.2.0; extra == "telemetry"
Requires-Dist: opentelemetry-instrumentation-fastapi; extra == "telemetry"
Provides-Extra: dev
Requires-Dist: stac_fastapi.eodag[server,telemetry]; extra == "dev"
Requires-Dist: geojson; extra == "dev"
Requires-Dist: httpx; extra == "dev"
Requires-Dist: importlib-metadata; extra == "dev"
Requires-Dist: mypy; extra == "dev"
Requires-Dist: pre-commit; extra == "dev"
Requires-Dist: pytest; extra == "dev"
Requires-Dist: pytest-asyncio; extra == "dev"
Requires-Dist: pytest-cov; extra == "dev"
Requires-Dist: pytest-mock; extra == "dev"
Requires-Dist: pytest-socket; extra == "dev"
Requires-Dist: pytest-html; extra == "dev"
Requires-Dist: responses; extra == "dev"
Requires-Dist: stdlib-list; extra == "dev"
Requires-Dist: tox; extra == "dev"
Requires-Dist: tox-uv; extra == "dev"
Requires-Dist: types-shapely; extra == "dev"
Dynamic: license-file
